kypymrt/Enums.py
kypymrt/__init__.py
kypymrt/kunyi_daq_monitor.py
kypymrt/kunyi_hil_test.py
kypymrt/kunyi_mrt.py
kypymrt/kunyi_project.py
kypymrt/kunyi_util.py
kypymrt/mrt.dll
kypymrt/mrt_strunctures.py
kypymrt/signal_daq.py
kypymrt/mrt_regression/TerminalTest.py
kypymrt/mrt_regression/__init__.py
kypymrt/mrt_regression/mrt_re_test.py
kypymrt/mrt_regression/stability_test.py
kypymrt/tests/__init__.py
kypymrt/tests/ee_help.py
kypymrt/tests/monitor_test.py
kypymrt/tests/multi_thread_test.py
kypymrt/tests/record_test.py
kypymrt/tests/test_hil_test.py
kypymrt/tests/test_main.py
kypymrt/tests/test_struct_ports.py
kypymrt/tests/util_fun_test.py
kypymrt-1.2.3.dist-info/LICENSE
kypymrt-1.2.3.dist-info/METADATA
kypymrt-1.2.3.dist-info/WHEEL
kypymrt-1.2.3.dist-info/top_level.txt
kypymrt-1.2.3.dist-info/RECORD
