Metadata-Version: 2.1
Name: kypymrt
Version: 1.2.3
Summary: mrt auto test
Home-page: 
Author: lyl
Author-email: lyulei66@163.com
Classifier: Programming Language :: Python :: 3
Classifier: License :: OSI Approved :: MIT License
Classifier: Operating System :: OS Independent
Requires-Python: >=3.6
License-File: LICENSE
